curethinkdb/__init__.py
curethinkdb/errors.py
curethinkdb/net.py
curethinkdb-0.0.1.dist-info/DESCRIPTION.rst
curethinkdb-0.0.1.dist-info/METADATA
curethinkdb-0.0.1.dist-info/RECORD
curethinkdb-0.0.1.dist-info/WHEEL
curethinkdb-0.0.1.dist-info/metadata.json
curethinkdb-0.0.1.dist-info/top_level.txt
