Metadata-Version: 2.0
Name: curethinkdb
Version: 0.0.1
Summary: Curio + RethinkDB: Async RethinkDB driver
Home-page: https://github.com/guyskk/curethinkdb
Author: guyskk
Author-email: guyskk@qq.com
License: MIT
Keywords: curio rethinkdb async driver
Platform: UNKNOWN
Classifier: Intended Audience :: Developers
Classifier: License :: OSI Approved :: MIT License
Classifier: Operating System :: OS Independent
Classifier: Programming Language :: Python :: 3 :: Only
Classifier: Topic :: Software Development :: Libraries :: Python Modules
Requires-Dist: rethinkdb
Requires-Dist: curio
